{
    "swagger": "2.0",
    "info": {
        "description": "coffe shop project",
        "title": "Coffee Shop API",
        "contact": {},
        "version": "1.0.0"
    },
    "host": "localhost:8888",
    "basePath": "/",
    "paths": {
        "/": {
            "get": {
                "description": "Retrieve all products from the system",
                "consumes": [
                    "application/json"
                ],
                "produces": [
                    "application/json"
                ],
                "tags": [
                    "products"
                ],
                "summary": "Get All Product",
                "responses": {
                    "200": {
                        "description": "OK",
                        "schema": {
                            "$ref": "#/definitions/models.Response"
                        }
                    },
                    "500": {
                        "description": "Internal Server Error",
                        "schema": {
                            "$ref": "#/definitions/models.Response"
                        }
                    }
                }
            }
        },
        "//historyorder/{id}": {
            "get": {
                "description": "Retrieve a specific order using its ID",
                "produces": [
                    "application/json"
                ],
                "tags": [
                    "orders"
                ],
                "summary": "Get Order by ID",
                "parameters": [
                    {
                        "type": "string",
                        "description": "Order ID",
                        "name": "id",
                        "in": "path",
                        "required": true
                    }
                ],
                "responses": {
                    "200": {
                        "description": "OK",
                        "schema": {
                            "$ref": "#/definitions/models.Response"
                        }
                    },
                    "404": {
                        "description": "Not Found",
                        "schema": {
                            "$ref": "#/definitions/models.Response"
                        }
                    }
                }
            }
        },
        "/admin/category": {
            "get": {
                "security": [
                    {
                        "BearerAuth": []
                    }
                ],
                "description": "Retrieve all category from the database",
                "consumes": [
                    "application/json"
                ],
                "produces": [
                    "application/json"
                ],
                "tags": [
                    "category"
                ],
                "summary": "Get All Category",
                "responses": {
                    "200": {
                        "description": "OK",
                        "schema": {
                            "$ref": "#/definitions/models.Response"
                        }
                    },
                    "500": {
                        "description": "Internal Server Error",
                        "schema": {
                            "$ref": "#/definitions/models.Response"
                        }
                    }
                }
            },
            "post": {
                "security": [
                    {
                        "BearerAuth": []
                    }
                ],
                "description": "Create a new category",
                "consumes": [
                    "application/json"
                ],
                "produces": [
                    "application/json"
                ],
                "tags": [
                    "category"
                ],
                "summary": "Add Category",
                "parameters": [
                    {
                        "description": "Category Data",
                        "name": "category",
                        "in": "body",
                        "required": true,
                        "schema": {
                            "$ref": "#/definitions/models.Category"
                        }
                    }
                ],
                "responses": {
                    "200": {
                        "description": "OK",
                        "schema": {
                            "$ref": "#/definitions/models.Response"
                        }
                    },
                    "400": {
                        "description": "Bad Request",
                        "schema": {
                            "$ref": "#/definitions/models.Response"
                        }
                    },
                    "500": {
                        "description": "Internal Server Error",
                        "schema": {
                            "$ref": "#/definitions/models.Response"
                        }
                    }
                }
            }
        },
        "/admin/category/{id}": {
            "get": {
                "security": [
                    {
                        "BearerAuth": []
                    }
                ],
                "description": "Retrieve a single category by its ID parameter",
                "consumes": [
                    "application/json"
                ],
                "produces": [
                    "application/json"
                ],
                "tags": [
                    "category"
                ],
                "summary": "Get Category by ID",
                "parameters": [
                    {
                        "type": "integer",
                        "description": "Category ID",
                        "name": "id",
                        "in": "path",
                        "required": true
                    }
                ],
                "responses": {
                    "200": {
                        "description": "OK",
                        "schema": {
                            "$ref": "#/definitions/models.Response"
                        }
                    },
                    "404": {
                        "description": "Not Found",
                        "schema": {
                            "$ref": "#/definitions/models.Response"
                        }
                    }
                }
            },
            "put": {
                "security": [
                    {
                        "BearerAuth": []
                    }
                ],
                "description": "Update an existing category by ID",
                "consumes": [
                    "application/json"
                ],
                "produces": [
                    "application/json"
                ],
                "tags": [
                    "category"
                ],
                "summary": "Update Category",
                "parameters": [
                    {
                        "type": "integer",
                        "description": "Category ID",
                        "name": "id",
                        "in": "path",
                        "required": true
                    },
                    {
                        "description": "Category Data",
                        "name": "category",
                        "in": "body",
                        "required": true,
                        "schema": {
                            "$ref": "#/definitions/models.Category"
                        }
                    }
                ],
                "responses": {
                    "200": {
                        "description": "OK",
                        "schema": {
                            "$ref": "#/definitions/models.Response"
                        }
                    },
                    "400": {
                        "description": "Bad Request",
                        "schema": {
                            "$ref": "#/definitions/models.Response"
                        }
                    },
                    "404": {
                        "description": "Not Found",
                        "schema": {
                            "$ref": "#/definitions/models.Response"
                        }
                    }
                }
            },
            "delete": {
                "security": [
                    {
                        "BearerAuth": []
                    }
                ],
                "description": "Delete category by ID",
                "produces": [
                    "application/json"
                ],
                "tags": [
                    "category"
                ],
                "summary": "Delete Category",
                "parameters": [
                    {
                        "type": "integer",
                        "description": "Category ID",
                        "name": "id",
                        "in": "path",
                        "required": true
                    }
                ],
                "responses": {
                    "200": {
                        "description": "OK",
                        "schema": {
                            "$ref": "#/definitions/models.Response"
                        }
                    },
                    "404": {
                        "description": "Not Found",
                        "schema": {
                            "$ref": "#/definitions/models.Response"
                        }
                    }
                }
            }
        },
        "/admin/products": {
            "post": {
                "description": "Add a new product to the system",
                "consumes": [
                    "application/json"
                ],
                "produces": [
                    "application/json"
                ],
                "tags": [
                    "products"
                ],
                "summary": "Add Product",
                "parameters": [
                    {
                        "description": "Product Data",
                        "name": "product",
                        "in": "body",
                        "required": true,
                        "schema": {
                            "$ref": "#/definitions/models.Product"
                        }
                    }
                ],
                "responses": {
                    "200": {
                        "description": "OK",
                        "schema": {
                            "$ref": "#/definitions/models.Response"
                        }
                    },
                    "400": {
                        "description": "Bad Request",
                        "schema": {
                            "$ref": "#/definitions/models.Response"
                        }
                    },
                    "500": {
                        "description": "Internal Server Error",
                        "schema": {
                            "$ref": "#/definitions/models.Response"
                        }
                    }
                }
            }
        },
        "/admin/products/{id}": {
            "put": {
                "description": "Update an existing product by ID",
                "consumes": [
                    "application/json"
                ],
                "produces": [
                    "application/json"
                ],
                "tags": [
                    "products"
                ],
                "summary": "Update Product",
                "parameters": [
                    {
                        "type": "integer",
                        "description": "Product ID",
                        "name": "id",
                        "in": "path",
                        "required": true
                    },
                    {
                        "description": "Product Data",
                        "name": "product",
                        "in": "body",
                        "required": true,
                        "schema": {
                            "$ref": "#/definitions/models.Product"
                        }
                    }
                ],
                "responses": {
                    "200": {
                        "description": "OK",
                        "schema": {
                            "$ref": "#/definitions/models.Response"
                        }
                    },
                    "400": {
                        "description": "Bad Request",
                        "schema": {
                            "$ref": "#/definitions/models.Response"
                        }
                    },
                    "404": {
                        "description": "Not Found",
                        "schema": {
                            "$ref": "#/definitions/models.Response"
                        }
                    }
                }
            },
            "delete": {
                "description": "Delete product by ID",
                "produces": [
                    "application/json"
                ],
                "tags": [
                    "products"
                ],
                "summary": "Delete Product",
                "parameters": [
                    {
                        "type": "integer",
                        "description": "Product ID",
                        "name": "id",
                        "in": "path",
                        "required": true
                    }
                ],
                "responses": {
                    "200": {
                        "description": "OK",
                        "schema": {
                            "$ref": "#/definitions/models.Response"
                        }
                    },
                    "404": {
                        "description": "Not Found",
                        "schema": {
                            "$ref": "#/definitions/models.Response"
                        }
                    }
                }
            }
        },
        "/auth/forgot-password": {
            "post": {
                "description": "Request OTP for password reset",
                "consumes": [
                    "application/json"
                ],
                "produces": [
                    "application/json"
                ],
                "tags": [
                    "auth"
                ],
                "summary": "Request forgot password",
                "parameters": [
                    {
                        "description": "Forgot password request",
                        "name": "req",
                        "in": "body",
                        "required": true,
                        "schema": {
                            "$ref": "#/definitions/models.AuthForgotPassword"
                        }
                    }
                ],
                "responses": {
                    "200": {
                        "description": "OK",
                        "schema": {
                            "$ref": "#/definitions/models.Response"
                        }
                    },
                    "400": {
                        "description": "Bad Request",
                        "schema": {
                            "$ref": "#/definitions/models.Response"
                        }
                    }
                }
            }
        },
        "/auth/login": {
            "post": {
                "description": "Authenticate user and generate JWT token",
                "consumes": [
                    "application/json"
                ],
                "produces": [
                    "application/json"
                ],
                "tags": [
                    "auth"
                ],
                "summary": "Login user",
                "parameters": [
                    {
                        "description": "Login credentials",
                        "name": "req",
                        "in": "body",
                        "required": true,
                        "schema": {
                            "$ref": "#/definitions/models.AuthLogin"
                        }
                    }
                ],
                "responses": {
                    "200": {
                        "description": "OK",
                        "schema": {
                            "$ref": "#/definitions/models.Response"
                        }
                    },
                    "400": {
                        "description": "Bad Request",
                        "schema": {
                            "$ref": "#/definitions/models.Response"
                        }
                    },
                    "500": {
                        "description": "Internal Server Error",
                        "schema": {
                            "$ref": "#/definitions/models.Response"
                        }
                    }
                }
            }
        },
        "/auth/register": {
            "post": {
                "description": "Register a new user to the system",
                "consumes": [
                    "application/json"
                ],
                "produces": [
                    "application/json"
                ],
                "tags": [
                    "auth"
                ],
                "summary": "Register new user",
                "parameters": [
                    {
                        "description": "Register credentials",
                        "name": "req",
                        "in": "body",
                        "required": true,
                        "schema": {
                            "$ref": "#/definitions/models.AuthRegister"
                        }
                    }
                ],
                "responses": {
                    "200": {
                        "description": "OK",
                        "schema": {
                            "$ref": "#/definitions/models.Response"
                        }
                    },
                    "400": {
                        "description": "Bad Request",
                        "schema": {
                            "$ref": "#/definitions/models.Response"
                        }
                    },
                    "500": {
                        "description": "Internal Server Error",
                        "schema": {
                            "$ref": "#/definitions/models.Response"
                        }
                    }
                }
            }
        },
        "/browseproduct": {
            "get": {
                "description": "Retrieve Browse Product from the system",
                "consumes": [
                    "application/json"
                ],
                "produces": [
                    "application/json"
                ],
                "tags": [
                    "products"
                ],
                "summary": "Get Browse Product",
                "responses": {
                    "200": {
                        "description": "OK",
                        "schema": {
                            "$ref": "#/definitions/models.Response"
                        }
                    },
                    "500": {
                        "description": "Internal Server Error",
                        "schema": {
                            "$ref": "#/definitions/models.Response"
                        }
                    }
                }
            }
        },
        "/cart": {
            "get": {
                "description": "Get the current user's cart",
                "produces": [
                    "application/json"
                ],
                "tags": [
                    "cart"
                ],
                "summary": "Get Cart",
                "responses": {
                    "200": {
                        "description": "OK",
                        "schema": {
                            "$ref": "#/definitions/models.Response"
                        }
                    },
                    "404": {
                        "description": "Not Found",
                        "schema": {
                            "$ref": "#/definitions/models.Response"
                        }
                    }
                }
            },
            "post": {
                "description": "Add a product to the user's cart",
                "consumes": [
                    "application/json"
                ],
                "produces": [
                    "application/json"
                ],
                "tags": [
                    "cart"
                ],
                "summary": "Add to Cart",
                "parameters": [
                    {
                        "description": "Add Cart Request",
                        "name": "req",
                        "in": "body",
                        "required": true,
                        "schema": {
                            "$ref": "#/definitions/models.AddCartRequest"
                        }
                    }
                ],
                "responses": {
                    "200": {
                        "description": "OK",
                        "schema": {
                            "$ref": "#/definitions/models.Response"
                        }
                    },
                    "400": {
                        "description": "Bad Request",
                        "schema": {
                            "$ref": "#/definitions/models.Response"
                        }
                    },
                    "401": {
                        "description": "Unauthorized",
                        "schema": {
                            "$ref": "#/definitions/models.Response"
                        }
                    }
                }
            },
            "delete": {
                "description": "Delete a product from the user's cart",
                "consumes": [
                    "application/json"
                ],
                "produces": [
                    "application/json"
                ],
                "tags": [
                    "cart"
                ],
                "summary": "Delete from Cart",
                "parameters": [
                    {
                        "description": "Delete Cart Item Request",
                        "name": "req",
                        "in": "body",
                        "required": true,
                        "schema": {
                            "$ref": "#/definitions/models.DeleteCartItem"
                        }
                    }
                ],
                "responses": {
                    "200": {
                        "description": "OK",
                        "schema": {
                            "$ref": "#/definitions/models.Response"
                        }
                    },
                    "400": {
                        "description": "Bad Request",
                        "schema": {
                            "$ref": "#/definitions/models.Response"
                        }
                    },
                    "404": {
                        "description": "Not Found",
                        "schema": {
                            "$ref": "#/definitions/models.Response"
                        }
                    }
                }
            }
        },
        "/historyorder": {
            "get": {
                "description": "Get the current user's order history",
                "produces": [
                    "application/json"
                ],
                "tags": [
                    "orders"
                ],
                "summary": "Order History",
                "responses": {
                    "200": {
                        "description": "OK",
                        "schema": {
                            "$ref": "#/definitions/models.Response"
                        }
                    },
                    "401": {
                        "description": "Unauthorized",
                        "schema": {
                            "$ref": "#/definitions/models.Response"
                        }
                    },
                    "404": {
                        "description": "Not Found",
                        "schema": {
                            "$ref": "#/definitions/models.Response"
                        }
                    }
                }
            }
        },
        "/orders": {
            "post": {
                "description": "Create an order from the user's current cart",
                "produces": [
                    "application/json"
                ],
                "tags": [
                    "orders"
                ],
                "summary": "Create Order",
                "responses": {
                    "200": {
                        "description": "OK",
                        "schema": {
                            "$ref": "#/definitions/models.Response"
                        }
                    },
                    "400": {
                        "description": "Bad Request",
                        "schema": {
                            "$ref": "#/definitions/models.Response"
                        }
                    },
                    "401": {
                        "description": "Unauthorized",
                        "schema": {
                            "$ref": "#/definitions/models.Response"
                        }
                    }
                }
            }
        },
        "/products/home": {
            "get": {
                "description": "Retrieve Product Home from the system",
                "consumes": [
                    "application/json"
                ],
                "produces": [
                    "application/json"
                ],
                "tags": [
                    "products"
                ],
                "summary": "Get Product Home",
                "responses": {
                    "200": {
                        "description": "OK",
                        "schema": {
                            "$ref": "#/definitions/models.Response"
                        }
                    },
                    "500": {
                        "description": "Internal Server Error",
                        "schema": {
                            "$ref": "#/definitions/models.Response"
                        }
                    }
                }
            }
        },
        "/products/reviews": {
            "get": {
                "description": "Retrieve Product Reviews from the system",
                "consumes": [
                    "application/json"
                ],
                "produces": [
                    "application/json"
                ],
                "tags": [
                    "products"
                ],
                "summary": "Get Product Reviews",
                "responses": {
                    "200": {
                        "description": "OK",
                        "schema": {
                            "$ref": "#/definitions/models.Response"
                        }
                    },
                    "500": {
                        "description": "Internal Server Error",
                        "schema": {
                            "$ref": "#/definitions/models.Response"
                        }
                    }
                }
            }
        },
        "/profile": {
            "get": {
                "description": "Get the profile of the currently logged-in user",
                "produces": [
                    "application/json"
                ],
                "tags": [
                    "profile"
                ],
                "summary": "Get My Profile",
                "responses": {
                    "200": {
                        "description": "OK",
                        "schema": {
                            "$ref": "#/definitions/models.Response"
                        }
                    },
                    "401": {
                        "description": "Unauthorized",
                        "schema": {
                            "$ref": "#/definitions/models.Response"
                        }
                    },
                    "404": {
                        "description": "Not Found",
                        "schema": {
                            "$ref": "#/definitions/models.Response"
                        }
                    }
                }
            },
            "put": {
                "description": "Update the profile of the currently logged-in user",
                "consumes": [
                    "application/json"
                ],
                "produces": [
                    "application/json"
                ],
                "tags": [
                    "profile"
                ],
                "summary": "Update Profile",
                "parameters": [
                    {
                        "description": "User Data",
                        "name": "user",
                        "in": "body",
                        "required": true,
                        "schema": {
                            "$ref": "#/definitions/models.User"
                        }
                    }
                ],
                "responses": {
                    "200": {
                        "description": "OK",
                        "schema": {
                            "$ref": "#/definitions/models.Response"
                        }
                    },
                    "400": {
                        "description": "Bad Request",
                        "schema": {
                            "$ref": "#/definitions/models.Response"
                        }
                    }
                }
            }
        },
        "/users": {
            "get": {
                "description": "Retrieve all users from the database",
                "produces": [
                    "application/json"
                ],
                "tags": [
                    "users"
                ],
                "summary": "Get All Users",
                "responses": {
                    "200": {
                        "description": "OK",
                        "schema": {
                            "$ref": "#/definitions/models.Response"
                        }
                    },
                    "500": {
                        "description": "Internal Server Error",
                        "schema": {
                            "$ref": "#/definitions/models.Response"
                        }
                    }
                }
            },
            "post": {
                "description": "AddUser Process",
                "consumes": [
                    "application/json"
                ],
                "produces": [
                    "application/json"
                ],
                "tags": [
                    "users"
                ],
                "summary": "AddUser Post",
                "responses": {
                    "200": {
                        "description": "OK",
                        "schema": {
                            "$ref": "#/definitions/models.Users"
                        }
                    },
                    "400": {
                        "description": "Bad Request",
                        "schema": {
                            "$ref": "#/definitions/models.Users"
                        }
                    }
                }
            }
        },
        "/users/{id}": {
            "get": {
                "description": "Retrieve a single user by its ID parameter",
                "consumes": [
                    "application/json"
                ],
                "produces": [
                    "application/json"
                ],
                "tags": [
                    "users"
                ],
                "summary": "Get user by ID",
                "parameters": [
                    {
                        "type": "integer",
                        "description": "User ID",
                        "name": "id",
                        "in": "path",
                        "required": true
                    }
                ],
                "responses": {
                    "200": {
                        "description": "OK",
                        "schema": {
                            "$ref": "#/definitions/models.Response"
                        }
                    },
                    "400": {
                        "description": "Bad Request",
                        "schema": {
                            "$ref": "#/definitions/models.Response"
                        }
                    },
                    "404": {
                        "description": "Not Found",
                        "schema": {
                            "$ref": "#/definitions/models.Response"
                        }
                    }
                }
            },
            "delete": {
                "description": "Delete user by ID",
                "produces": [
                    "application/json"
                ],
                "tags": [
                    "users"
                ],
                "summary": "Delete user",
                "parameters": [
                    {
                        "type": "integer",
                        "format": "int64",
                        "description": "User ID",
                        "name": "id",
                        "in": "path",
                        "required": true
                    }
                ],
                "responses": {
                    "200": {
                        "description": "OK",
                        "schema": {
                            "$ref": "#/definitions/models.Response"
                        }
                    },
                    "400": {
                        "description": "Bad Request",
                        "schema": {
                            "$ref": "#/definitions/models.Response"
                        }
                    },
                    "404": {
                        "description": "Not Found",
                        "schema": {
                            "$ref": "#/definitions/models.Response"
                        }
                    }
                }
            }
        }
    },
    "definitions": {
        "models.AddCartRequest": {
            "type": "object",
            "required": [
                "product_id",
                "quantity",
                "user_id"
            ],
            "properties": {
                "base_price": {
                    "type": "integer"
                },
                "product_id": {
                    "type": "integer"
                },
                "product_name": {
                    "type": "string"
                },
                "quantity": {
                    "type": "integer",
                    "minimum": 1
                },
                "size_name": {
                    "type": "string"
                },
                "user_id": {
                    "type": "integer"
                },
                "variant_name": {
                    "type": "string"
                }
            }
        },
        "models.AuthForgotPassword": {
            "type": "object",
            "required": [
                "email"
            ],
            "properties": {
                "email": {
                    "type": "string"
                }
            }
        },
        "models.AuthLogin": {
            "type": "object",
            "properties": {
                "address": {
                    "type": "string"
                },
                "created_at": {
                    "type": "string"
                },
                "email": {
                    "type": "string"
                },
                "full_name": {
                    "type": "string"
                },
                "id": {
                    "type": "integer"
                },
                "password": {
                    "type": "string"
                },
                "phone": {
                    "type": "string"
                },
                "pictures": {
                    "type": "string"
                },
                "role": {
                    "type": "string"
                }
            }
        },
        "models.AuthRegister": {
            "type": "object",
            "required": [
                "email",
                "full_name",
                "password"
            ],
            "properties": {
                "email": {
                    "type": "string"
                },
                "full_name": {
                    "type": "string"
                },
                "password": {
                    "type": "string",
                    "minLength": 6
                }
            }
        },
        "models.Category": {
            "type": "object",
            "properties": {
                "category_id": {
                    "type": "integer"
                },
                "category_name": {
                    "type": "string"
                }
            }
        },
        "models.DeleteCartItem": {
            "type": "object",
            "required": [
                "cart_item_id"
            ],
            "properties": {
                "cart_item_id": {
                    "type": "integer"
                }
            }
        },
        "models.Product": {
            "type": "object",
            "properties": {
                "discount": {
                    "type": "integer"
                },
                "id": {
                    "type": "integer"
                },
                "price": {
                    "type": "integer"
                },
                "product_desc": {
                    "type": "string"
                },
                "product_name": {
                    "type": "string"
                },
                "quantity": {
                    "type": "integer"
                }
            }
        },
        "models.Response": {
            "type": "object",
            "properties": {
                "message": {
                    "type": "string"
                },
                "results": {},
                "success": {
                    "type": "boolean"
                }
            }
        },
        "models.User": {
            "type": "object",
            "properties": {
                "address": {
                    "type": "string"
                },
                "email": {
                    "type": "string"
                },
                "full_name": {
                    "type": "string"
                },
                "id": {
                    "type": "integer"
                },
                "password": {
                    "type": "string"
                },
                "phone": {
                    "type": "string"
                },
                "pictures": {
                    "type": "string"
                }
            }
        },
        "models.Users": {
            "type": "object",
            "properties": {
                "address": {
                    "type": "string"
                },
                "email": {
                    "type": "string"
                },
                "full_name": {
                    "type": "string"
                },
                "id": {
                    "type": "integer"
                },
                "phone": {
                    "type": "string"
                },
                "pictures": {
                    "type": "string"
                }
            }
        }
    },
    "securityDefinitions": {
        "BearerAuth": {
            "description": "Masukkan token dengan format: Bearer \u003ctoken-anda\u003e",
            "type": "apiKey",
            "name": "Authorization",
            "in": "header"
        }
    }
}